rupindytetool/__init__.py
rupindytetool/rupindytetool.py
rupindytetool-1.0.0.dist-info/METADATA
rupindytetool-1.0.0.dist-info/WHEEL
rupindytetool-1.0.0.dist-info/entry_points.txt
rupindytetool-1.0.0.dist-info/top_level.txt
rupindytetool-1.0.0.dist-info/RECORD
