Metadata-Version: 2.1
Name: rupindytetool
Version: 1.0.0
Summary: Dyte task myawsometool by Rupin Patel.
Home-page: https://github.com/patel-rupin2000/dyte_test
Author: Rupin Patel
Author-email: patelrupin63@gmail.com
License: MIT
Classifier: Programming Language :: Python :: 3
Classifier: License :: OSI Approved :: MIT License
Classifier: Operating System :: OS Independent
Requires-Dist: backports.zoneinfo (==0.2.1)
Requires-Dist: certifi (==2022.5.18.1)
Requires-Dist: cffi (==1.15.0)
Requires-Dist: charset-normalizer (==2.0.12)
Requires-Dist: configobj (==5.0.6)
Requires-Dist: Deprecated (==1.2.13)
Requires-Dist: gitdb (==4.0.9)
Requires-Dist: GitPython (==3.1.27)
Requires-Dist: giturlparse (==0.10.0)
Requires-Dist: idna (==3.3)
Requires-Dist: numpy (==1.22.4)
Requires-Dist: pandas (==1.4.2)
Requires-Dist: pycparser (==2.21)
Requires-Dist: PyGithub (==1.55)
Requires-Dist: pyjsparser (==2.7.1)
Requires-Dist: PyJWT (==2.4.0)
Requires-Dist: PyNaCl (==1.5.0)
Requires-Dist: python-dateutil (==2.8.2)
Requires-Dist: pytz (==2022.1)
Requires-Dist: pytz-deprecation-shim (==0.1.0.post0)
Requires-Dist: repo (==0.1.0)
Requires-Dist: requests (==2.27.1)
Requires-Dist: six (==1.16.0)
Requires-Dist: smmap (==5.0.0)
Requires-Dist: tzdata (==2022.1)
Requires-Dist: tzlocal (==4.2)
Requires-Dist: urllib3 (==1.26.9)
Requires-Dist: wget (==3.2)
Requires-Dist: wrapt (==1.14.1)
